plotly_plate/__init__.py
plotly_plate/plate.py
plotly_plate/utils/__init__.py
plotly_plate/utils/plate_utils.py
plotly_plate-0.1.0.dist-info/LICENSE
plotly_plate-0.1.0.dist-info/METADATA
plotly_plate-0.1.0.dist-info/WHEEL
plotly_plate-0.1.0.dist-info/RECORD
